invode/__init__.py
invode/error_functions.py
invode/optimizer.py
invode/optimizer_old.py
invode/sampling.py
invode/sensitivity.py
invode/utils.py
invode-0.1.2.dist-info/licenses/LICENSE
invode-0.1.2.dist-info/METADATA
invode-0.1.2.dist-info/WHEEL
invode-0.1.2.dist-info/top_level.txt
invode-0.1.2.dist-info/RECORD
