Metadata-Version: 2.4
Name: invode
Version: 0.1.2
Summary: Inverse-ODE fitting and sensitivity tools
Author: Raunak Dey
License-Expression: MIT
Project-URL: Homepage, https://github.com/RaunakDey/InvODE
Project-URL: Issues, https://github.com/RaunakDey/InvODE/issues
Project-URL: Docs, https://raunakdey.github.io/InvODE
Keywords: ode,inverse-problems,differential-equations
Classifier: Programming Language :: Python :: 3
Classifier: Operating System :: OS Independent
Classifier: Topic :: Scientific/Engineering
Requires-Python: >=3.9
License-File: LICENSE
Requires-Dist: numpy>=1.23
Requires-Dist: pandas>=1.5
Requires-Dist: scipy>=1.9
Requires-Dist: matplotlib>=3.6
Requires-Dist: tqdm>=4.64
Requires-Dist: seaborn>=0.12
Dynamic: license-file
